LICENSE
MANIFEST.in
README.rst
setup.py
src/gluonnlp/__init__.py
src/gluonnlp/_constants.py
src/gluonnlp/base.py
src/gluonnlp.egg-info/PKG-INFO
src/gluonnlp.egg-info/SOURCES.txt
src/gluonnlp.egg-info/dependency_links.txt
src/gluonnlp.egg-info/requires.txt
src/gluonnlp.egg-info/top_level.txt
src/gluonnlp.egg-info/zip-safe
src/gluonnlp/calibration/__init__.py
src/gluonnlp/calibration/collector.py
src/gluonnlp/data/__init__.py
src/gluonnlp/data/baidu_ernie_data.py
src/gluonnlp/data/candidate_sampler.py
src/gluonnlp/data/classification.py
src/gluonnlp/data/conll.py
src/gluonnlp/data/dataloader.py
src/gluonnlp/data/dataset.py
src/gluonnlp/data/datasetloader.py
src/gluonnlp/data/fast_bert_tokenizer.c
src/gluonnlp/data/fast_bert_tokenizer.pyx
src/gluonnlp/data/glue.py
src/gluonnlp/data/intent_slot.py
src/gluonnlp/data/question_answering.py
src/gluonnlp/data/registry.py
src/gluonnlp/data/sampler.py
src/gluonnlp/data/sentiment.py
src/gluonnlp/data/stream.py
src/gluonnlp/data/super_glue.py
src/gluonnlp/data/transforms.py
src/gluonnlp/data/translation.py
src/gluonnlp/data/utils.py
src/gluonnlp/data/word_embedding_evaluation.py
src/gluonnlp/data/batchify/__init__.py
src/gluonnlp/data/batchify/batchify.py
src/gluonnlp/data/batchify/embedding.py
src/gluonnlp/data/batchify/language_model.py
src/gluonnlp/data/bert/__init__.py
src/gluonnlp/data/bert/glue.py
src/gluonnlp/data/bert/squad.py
src/gluonnlp/data/corpora/__init__.py
src/gluonnlp/data/corpora/google_billion_word.py
src/gluonnlp/data/corpora/large_text_compression_benchmark.py
src/gluonnlp/data/corpora/wikitext.py
src/gluonnlp/data/xlnet/__init__.py
src/gluonnlp/data/xlnet/squad.py
src/gluonnlp/embedding/__init__.py
src/gluonnlp/embedding/evaluation.py
src/gluonnlp/embedding/token_embedding.py
src/gluonnlp/initializer/__init__.py
src/gluonnlp/initializer/initializer.py
src/gluonnlp/loss/__init__.py
src/gluonnlp/loss/activation_regularizer.py
src/gluonnlp/loss/label_smoothing.py
src/gluonnlp/loss/loss.py
src/gluonnlp/metric/__init__.py
src/gluonnlp/metric/length_normalized_loss.py
src/gluonnlp/metric/masked_accuracy.py
src/gluonnlp/model/__init__.py
src/gluonnlp/model/attention_cell.py
src/gluonnlp/model/bert.py
