Metadata-Version: 2.1
Name: gluonnlp
Version: 0.10.0
Summary: MXNet Gluon NLP Toolkit
Home-page: https://github.com/dmlc/gluon-nlp
Author: Gluon NLP Toolkit Contributors
Author-email: mxnet-gluon@amazon.com
License: Apache-2.0
Platform: UNKNOWN
Requires-Python: >=3.5
Provides-Extra: extras
Provides-Extra: dev
